odoo/addons/web_widget_datepicker_fulloptions/README.rst
odoo/addons/web_widget_datepicker_fulloptions/__init__.py
odoo/addons/web_widget_datepicker_fulloptions/__manifest__.py
odoo/addons/web_widget_datepicker_fulloptions/i18n/it.po
odoo/addons/web_widget_datepicker_fulloptions/i18n/pt_BR.po
odoo/addons/web_widget_datepicker_fulloptions/i18n/tr.po
odoo/addons/web_widget_datepicker_fulloptions/i18n/web_widget_datepicker_fulloptions.pot
odoo/addons/web_widget_datepicker_fulloptions/readme/CONTRIBUTORS.rst
odoo/addons/web_widget_datepicker_fulloptions/readme/DESCRIPTION.rst
odoo/addons/web_widget_datepicker_fulloptions/static/description/change.png
odoo/addons/web_widget_datepicker_fulloptions/static/description/icon.png
odoo/addons/web_widget_datepicker_fulloptions/static/description/index.html
odoo/addons/web_widget_datepicker_fulloptions/static/src/js/web_widget_datepicker_fulloptions.esm.js
odoo_addon_web_widget_datepicker_fulloptions-16.0.1.0.0.3.dist-info/METADATA
odoo_addon_web_widget_datepicker_fulloptions-16.0.1.0.0.3.dist-info/WHEEL
odoo_addon_web_widget_datepicker_fulloptions-16.0.1.0.0.3.dist-info/top_level.txt
odoo_addon_web_widget_datepicker_fulloptions-16.0.1.0.0.3.dist-info/RECORD
